csu/__init__.py
csu/admin.py
csu/conf.py
csu/consts.py
csu/enums.py
csu/env.py
csu/exceptions.py
csu/export.py
csu/fixups.py
csu/gettext.py
csu/gettext_lazy.py
csu/logging.py
csu/management.py
csu/models.py
csu/query.py
csu/routers.py
csu/service.py
csu/test_consts.py
csu/test_env.py
csu/test_exceptions.py
csu/test_logging.py
csu/test_management.py
csu/test_service.py
csu/test_timezones.py
csu/test_utils.py
csu/test_xml.py
csu/timezones.py
csu/utils.py
csu/views.py
csu/wsgi.py
csu/xml.py
csu/drf/__init__.py
csu/drf/auth.py
csu/drf/fields.py
csu/drf/forms.py
csu/drf/perms.py
csu/drf/phonenumber.py
csu/drf/serializers.py
csu/drf/test_auth.py
csu/drf/test_fields.py
csu/drf/test_forms.py
csu/drf/test_phonenumber.py
csu/drf/test_serializers.py
csu/drf/views.py
csu/forms/__init__.py
csu/forms/crispy.py
csu/forms/fields.py
csu/locale/ro/LC_MESSAGES/django.mo
csu/locale/ro/LC_MESSAGES/django.po
csu/templates/api_exception.html
csu/templates/forms/widgets/opaquewidget.html
csu/worker/__init__.py
csu/worker/admin.py
csu/worker/asgi.py
csu/worker/engine.py
csu/worker/enums.py
csu/worker/job.py
csu/worker/models.py
csu/worker/registry.py
csu-1.19.8.dist-info/licenses/LICENSE
csu-1.19.8.dist-info/METADATA
csu-1.19.8.dist-info/WHEEL
csu-1.19.8.dist-info/top_level.txt
csu-1.19.8.dist-info/RECORD
