Metadata-Version: 2.4
Name: csu
Version: 1.19.8
Summary: Clean Slate Utils - bunch of utility code, mostly Django/DRF specific.
Author-email: Ionel Cristian Mărieș <contact@ionelmc.ro>
License-Expression: BSD-2-Clause
Project-URL: Sources, https://github.com/ionelmc/python-csu
Project-URL: Changelog, https://github.com/ionelmc/python-csu/blob/master/CHANGELOG.rst
Project-URL: Issue Tracker, https://github.com/ionelmc/python-csu/issues
Classifier: Development Status :: 5 - Production/Stable
Classifier: Intended Audience :: Developers
Classifier: Operating System :: Unix
Classifier: Operating System :: POSIX
Classifier: Operating System :: Microsoft :: Windows
Classifier: Programming Language :: Python
Classifier: Programming Language :: Python :: 3
Classifier: Programming Language :: Python :: 3 :: Only
Classifier: Programming Language :: Python :: 3.9
Classifier: Programming Language :: Python :: 3.10
Classifier: Programming Language :: Python :: 3.11
Classifier: Programming Language :: Python :: 3.12
Classifier: Programming Language :: Python :: 3.13
Classifier: Programming Language :: Python :: 3.14
Classifier: Programming Language :: Python :: Implementation :: CPython
Classifier: Programming Language :: Python :: Implementation :: PyPy
Classifier: Topic :: Utilities
Requires-Python: >=3.14
License-File: LICENSE
Provides-Extra: http
Requires-Dist: httpx; extra == "http"
Provides-Extra: xml
Requires-Dist: defusedxml; extra == "xml"
Provides-Extra: django
Requires-Dist: django; extra == "django"
Requires-Dist: djangorestframework; extra == "django"
Requires-Dist: django-crispy-forms; extra == "django"
Requires-Dist: django-import-export; extra == "django"
Provides-Extra: phonenumber
Requires-Dist: phonenumberslite; extra == "phonenumber"
Requires-Dist: django-phonenumber-field; extra == "phonenumber"
Dynamic: license-file
